{
  "page_number": 51,
  "account_holder_name": null,
  "transactions": [
    {
      "date": "1405/01/25",
      "time": "17:58:12",
      "description": "برداشت از سپرده بابت کارمزد انتقال پایا - شماره پیگیری تراکنش اصلی 140501250562837916",
      "deposit": 0.0,
      "withdrawal": 60000.0,
      "balance": 586146604.0,
      "source_page": 51,
      "row_order": 0
    },
    {
      "date": "1405/01/25",
      "time": "17:58:12",
      "description": "انتقال پایا به شماره شبا IR740120010000003075078152 بانک ملت بنام: شهناز بازرگانی - شماره پیگیری تراکنش: 140501250562837916",
      "deposit": 0.0,
      "withdrawal": 600000000.0,
      "balance": 586206604.0,
      "source_page": 51,
      "row_order": 1
    },
    {
      "date": "1405/01/25",
      "time": "14:54:15",
      "description": "انتقال از سپرده سامان از طریق موبایلت شبا مبدا: IR250560088180000617030001 - شماره سند: 1405518632965",
      "deposit": 300000000.0,
      "withdrawal": 0.0,
      "balance": 1186206604.0,
      "source_page": 51,
      "row_order": 2
    },
    {
      "date": "1405/01/25",
      "time": "13:30:18",
      "description": "انتقال به سپرده بلو - شماره سپرده: 611828005529515401 بنام: رضا ابراهیمی - شماره سند: 1405516849536",
      "deposit": 0.0,
      "withdrawal": 10000000.0,
      "balance": 886206604.0,
      "source_page": 51,
      "row_order": 3
    },
    {
      "date": "1405/01/25",
      "time": "12:39:24",
      "description": "برداشت از سپرده بابت کارمزد انتقال کارت به کارت-تراکنش اصلی ش م 177615776413 ش پ 981052",
      "deposit": 0.0,
      "withdrawal": 15400.0,
      "balance": 896206604.0,
      "source_page": 51,
      "row_order": 4
    },
    {
      "date": "1405/01/25",
      "time": "12:39:24",
      "description": "انتقال به کارت شماره: ****-****-****-**** بنام: حنیفه نوری از درگاه اینترنتی بانک سامان 10000006 - ش م: 177615776413 ش پ: 981052",
      "deposit": 0.0,
      "withdrawal": 30000000.0,
      "balance": 896222004.0,
      "source_page": 51,
      "row_order": 5
    },
    {
      "date": "1405/01/25",
      "time": "11:22:54",
      "description": "انتقال پل از شماره شبا IR040170000000373351530001 بانک ملی بنام حاتمی - کد پیگیری تراکنش: 140501250173090029927112253 - بهزاد",
      "deposit": 750000000.0,
      "withdrawal": 0.0,
      "balance": 926222004.0,
      "source_page": 51,
      "row_order": 6
    },
    {
      "date": "1405/01/25",
      "time": "09:18:36",
      "description": "خرید کالا و خدمات از پایانه فروش 31118232 پرداخت الکترونیک سامان ش م 860504476728 ش پ 435184",
      "deposit": 0.0,
      "withdrawal": 1087800.0,
      "balance": 176222004.0,
      "source_page": 51,
      "row_order": 7
    },
    {
      "date": "1405/01/24",
      "time": "21:50:08",
      "description": "خرید کالا و خدمات از پایانه فروش 08164088 به پرداخت ملت ش م 341948990263 ش پ 990263",
      "deposit": 0.0,
      "withdrawal": 5720000.0,
      "balance": 177309804.0,
      "source_page": 51,
      "row_order": 8
    },
    {
      "date": "1405/01/24",
      "time": "15:07:53",
      "description": "برداشت از سپرده بابت کارمزد انتقال کارت به کارت-تراکنش اصلی ش م 177608027244 ش پ 362376",
      "deposit": 0.0,
      "withdrawal": 9000.0,
      "balance": 183029804.0,
      "source_page": 51,
      "row_order": 9
    },
    {
      "date": "1405/01/24",
      "time": "15:07:53",
      "description": "انتقال به کارت شماره: ****-****-****-**** بنام: امیررضا عطاردی از درگاه اینترنتی بانک سامان 10000006 - ش م: 177608027244 ش پ: 362376",
      "deposit": 0.0,
      "withdrawal": 1400000.0,
      "balance": 183038804.0,
      "source_page": 51,
      "row_order": 10
    },
    {
      "date": "1405/01/24",
      "time": "14:04:56",
      "description": "انتقال به سپرده بلو - شماره سپرده: 611828006548487602 بنام: شهرام شادپور - شماره سند: 1405494066869",
      "deposit": 0.0,
      "withdrawal": 6000000.0,
      "balance": 184438804.0,
      "source_page": 51,
      "row_order": 11
    },
    {
      "date": "1405/01/24",
      "time": "13:39:28",
      "description": "برداشت از سپرده بابت کارمزد انتقال کارت به کارت-تراکنش اصلی ش م 177607496768 ش پ 665851",
      "deposit": 0.0,
      "withdrawal": 15400.0,
      "balance": 190438804.0,
      "source_page": 51,
      "row_order": 12
    },
    {
      "date": "1405/01/24",
      "time": "13:39:28",
      "description": "انتقال به کارت شماره: ****-****-****-**** بنام: دیمن قاسمی از درگاه اینترنتی بانک سامان 10000006 - ش م: 177607496768 ش پ: 665851",
      "deposit": 0.0,
      "withdrawal": 27800000.0,
      "balance": 190454204.0,
      "source_page": 51,
      "row_order": 13
    },
    {
      "date": "1405/01/24",
      "time": "12:12:15",
      "description": "برداشت از سپرده بابت کارمزد انتقال کارت به کارت-تراکنش اصلی ش م 177606973508 ش پ 585590",
      "deposit": 0.0,
      "withdrawal": 12200.0,
      "balance": 218254204.0,
      "source_page": 51,
      "row_order": 14
    },
    {
      "date": "1405/01/24",
      "time": "12:12:15",
      "description": "انتقال به کارت شماره: ****-****-****-**** بنام: داود هادی زاده از درگاه اینترنتی بانک سامان 10000006 - ش م: 177606973508 ش پ: 585590",
      "deposit": 0.0,
      "withdrawal": 20000000.0,
      "balance": 218266404.0,
      "source_page": 51,
      "row_order": 15
    },
    {
      "date": "1405/01/24",
      "time": "09:48:12",
      "description": "انتقال به سپرده بلو - شماره سپرده: 611828005124733101 بنام: فاطمه فلاح پور - شماره سند: 1405487806281",
      "deposit": 0.0,
      "withdrawal": 300000000.0,
      "balance": 238266404.0,
      "source_page": 51,
      "row_order": 16
    },
    {
      "date": "1405/01/23",
      "time": "22:39:03",
      "description": "خرید کالا و خدمات از پایانه فروش 71275629 پرداخت الکترونیک پاسارگاد ۲ ش م 142335615770 ش پ 039758",
      "deposit": 0.0,
      "withdrawal": 100000.0,
      "balance": 538266404.0,
      "source_page": 51,
      "row_order": 17
    },
    {
      "date": "1405/01/23",
      "time": "21:04:36",
      "description": "خرید کالا و خدمات از پایانه فروش 99331562 تجارت الکترونیک پارسیان ش م 749919128533 ش پ 758534",
      "deposit": 0.0,
      "withdrawal": 11795900.0,
      "balance": 538366404.0,
      "source_page": 51,
      "row_order": 18
    },
    {
      "date": "1405/01/23",
      "time": "20:53:44",
      "description": "برداشت از سپرده بابت کارمزد انتقال کارت به کارت-تراکنش اصلی ش م 177601462355 ش پ 219659",
      "deposit": 0.0,
      "withdrawal": 12200.0,
      "balance": 550162304.0,
      "source_page": 51,
      "row_order": 19
    },
    {
      "date": "1405/01/23",
      "time": "20:53:44",
      "description": "انتقال به کارت شماره: ****-****-****-**** بنام: فرهاد ملکی از درگاه اینترنتی بانک سامان 10000006 - ش م: 177601462355 ش پ: 219659",
      "deposit": 0.0,
      "withdrawal": 12000000.0,
      "balance": 550174504.0,
      "source_page": 51,
      "row_order": 20
    },
    {
      "date": "1405/01/23",
      "time": "15:27:02",
      "description": "خرید کالا و خدمات از پایانه فروش 21554091 پرداخت الکترونیک سامان ش م 860455958837 ش پ 522293",
      "deposit": 0.0,
      "withdrawal": 8300000.0,
      "balance": 562174504.0,
      "source_page": 51,
      "row_order": 21
    },
    {
      "date": "1405/01/23",
      "time": "15:16:50",
      "description": "خرید کالا و خدمات از پایانه فروش 31599739 نوین پرداخت آرین ۲ ش م 515796162966 ش پ 289290",
      "deposit": 0.0,
      "withdrawal": 3000000.0,
      "balance": 570474504.0,
      "source_page": 51,
      "row_order": 22
    },
    {
      "date": "1405/01/23",
      "time": "12:15:10",
      "description": "انتقال به سپرده بلو - شماره سپرده: 611828005301633401 بنام: رادیار جعفرپور - شماره سند: 1405466925777",
      "deposit": 0.0,
      "withdrawal": 405000000.0,
      "balance": 573474504.0,
      "source_page": 51,
      "row_order": 23
    },
    {
      "date": "1405/01/23",
      "time": "10:28:38",
      "description": "برداشت از سپرده بابت کارمزد انتقال کارت به کارت-تراکنش اصلی ش م 610210082658 ش پ 082658",
      "deposit": 0.0,
      "withdrawal": 31400.0,
      "balance": 978474504.0,
      "source_page": 51,
      "row_order": 24
    },
    {
      "date": "1405/01/23",
      "time": "10:28:38",
      "description": "انتقال به کارت شماره: ****-****-****-**** بنام: علی زیرک از خودپرداز بانک دی 00018265 - ش م: 610210082658 ش پ: 082658",
      "deposit": 0.0,
      "withdrawal": 71000000.0,
      "balance": 978505904.0,
      "source_page": 51,
      "row_order": 25
    },
    {
      "date": "1405/01/23",
      "time": "10:18:58",
      "description": "خرید کالا و خدمات از پایانه فروش 99064642 مبنا کارت آریا (اینفوتک) ش م 129605333638 ش پ 333638",
      "deposit": 0.0,
      "withdrawal": 197055000.0,
      "balance": 1049505904.0,
      "source_page": 51,
      "row_order": 26
    },
    {
      "date": "1405/01/23",
      "time": "04:46:25",
      "description": "انتقال پایا از شماره شبا IR340590038481302229017002 بانک سینا بنام: پیمان احمدی - شماره پیگیری تراکنش: 14050122059213304506",
      "deposit": 1000000000.0,
      "withdrawal": 0.0,
      "balance": 1246560904.0,
      "source_page": 51,
      "row_order": 27
    },
    {
      "date": "1405/01/22",
      "time": "20:57:17",
      "description": "برداشت از سپرده بابت کارمزد انتقال کارت به کارت-تراکنش اصلی ش م 177592843641 ش پ 225831",
      "deposit": 0.0,
      "withdrawal": 9000.0,
      "balance": 246560904.0,
      "source_page": 51,
      "row_order": 28
    },
    {
      "date": "1405/01/22",
      "time": "20:57:17",
      "description": "انتقال به کارت شماره: ****-****-****-**** بنام: فرهاد محمدی کبودچشمه از درگاه اینترنتی بانک سامان 10000006 - ش م: 177592843641 ش پ: 225831",
      "deposit": 0.0,
      "withdrawal": 4000000.0,
      "balance": 246569904.0,
      "source_page": 51,
      "row_order": 29
    },
    {
      "date": "1405/01/22",
      "time": "18:41:44",
      "description": "برداشت از سپرده بابت کارمزد انتقال پایا - شماره پیگیری تراکنش اصلی 140501220562870467",
      "deposit": 0.0,
      "withdrawal": 60000.0,
      "balance": 250569904.0,
      "source_page": 51,
      "row_order": 30
    },
    {
      "date": "1405/01/22",
      "time": "18:41:44",
      "description": "انتقال پایا به شماره شبا IR740120010000003075078152 بانک ملت بنام: شهناز بازرگانی - شماره پیگیری تراکنش: 140501220562870467",
      "deposit": 0.0,
      "withdrawal": 600000000.0,
      "balance": 250629904.0,
      "source_page": 51,
      "row_order": 31
    },
    {
      "date": "1405/01/22",
      "time": "17:05:17",
      "description": "انتقال به سپرده بلو - شماره سپرده: 611828005917468101 بنام: مانی عربزاده - شماره سند: 1405448983346",
      "deposit": 0.0,
      "withdrawal": 2000000.0,
      "balance": 850629904.0,
      "source_page": 51,
      "row_order": 32
    },
    {
      "date": "1405/01/22",
      "time": "16:38:00",
      "description": "خرید کالا و خدمات از پایانه فروش 08830685 به پرداخت ملت ش م 341704486737 ش پ 486737",
      "deposit": 0.0,
      "withdrawal": 850000.0,
      "balance": 852629904.0,
      "source_page": 51,
      "row_order": 33
    },
    {
      "date": "1405/01/22",
      "time": "16:27:17",
      "description": "خرید کالا و خدمات از پایانه فروش 31599739 نوین پرداخت آرین ۲ ش م 515782438254 ش پ 516740",
      "deposit": 0.0,
      "withdrawal": 10000000.0,
      "balance": 853479904.0,
      "source_page": 51,
      "row_order": 34
    },
    {
      "date": "1405/01/22",
      "time": "16:26:47",
      "description": "خرید کالا و خدمات از پایانه فروش 31599739 نوین پرداخت آرین ۲ ش م 515782434919 ش پ 508305",
      "deposit": 0.0,
      "withdrawal": 7000000.0,
      "balance": 863479904.0,
      "source_page": 51,
      "row_order": 35
    },
    {
      "date": "1405/01/22",
      "time": "15:55:02",
      "description": "انتقال به سپرده بلو - شماره سپرده: 611828005707107501 بنام: امیررضا عطاردی - شماره سند: 1405447360722",
      "deposit": 0.0,
      "withdrawal": 5200000.0,
      "balance": 870479904.0,
      "source_page": 51,
      "row_order": 36
    },
    {
      "date": "1405/01/22",
      "time": "15:40:19",
      "description": "انتقال به سپرده بلو - شماره سپرده: 611828006097705801 بنام: اقدس سلامت - شماره سند: 1405447063658",
      "deposit": 0.0,
      "withdrawal": 50000000.0,
      "balance": 875679904.0,
      "source_page": 51,
      "row_order": 37
    },
    {
      "date": "1405/01/22",
      "time": "14:28:59",
      "description": "انتقال به سپرده بلو - شماره سپرده: 611828005707107501 بنام: امیررضا عطاردی - شماره سند: 1405445626678",
      "deposit": 0.0,
      "withdrawal": 3600000.0,
      "balance": 925679904.0,
      "source_page": 51,
      "row_order": 38
    },
    {
      "date": "1405/01/22",
      "time": "11:53:05",
      "description": "برداشت از سپرده بابت کارمزد انتقال کارت به کارت-تراکنش اصلی ش م 177589578515 ش پ 506122",
      "deposit": 0.0,
      "withdrawal": 28200.0,
      "balance": 929279904.0,
      "source_page": 51,
      "row_order": 39
    },
    {
      "date": "1405/01/22",
      "time": "11:53:05",
      "description": "انتقال به کارت شماره: ****-****-****-**** بنام: علی اکبری اردکانی از درگاه اینترنتی بانک سامان 10000006 - ش م: 177589578515 ش پ: 506122",
      "deposit": 0.0,
      "withdrawal": 67000000.0,
      "balance": 929308104.0,
      "source_page": 51,
      "row_order": 40
    },
    {
      "date": "1405/01/22",
      "time": "09:39:08",
      "description": "خرید کالا و خدمات از پایانه فروش 20023878 ساین کارت ۲ ش م 114601945194 ش پ 545194",
      "deposit": 0.0,
      "withdrawal": 555000.0,
      "balance": 996308104.0,
      "source_page": 51,
      "row_order": 41
    },
    {
      "date": "1405/01/21",
      "time": "20:00:47",
      "description": "برداشت از سپرده بابت کارمزد انتقال کارت به کارت-تراکنش اصلی ش م 177583864711 ش پ 343937",
      "deposit": 0.0,
      "withdrawal": 12200.0,
      "balance": 996863104.0,
      "source_page": 51,
      "row_order": 42
    },
    {
      "date": "1405/01/21",
      "time": "20:00:47",
      "description": "انتقال به کارت شماره: ****-****-****-**** بنام: فرهاد ملکی از درگاه اینترنتی بانک سامان 10000006 - ش م: 177583864711 ش پ: 343937",
      "deposit": 0.0,
      "withdrawal": 12000000.0,
      "balance": 996875304.0,
      "source_page": 51,
      "row_order": 43
    },
    {
      "date": "1405/01/21",
      "time": "17:11:42",
      "description": "خرید کالا و خدمات از پایانه فروش 44266057 تجارت الکترونیک پارسیان ش م 749895339394 ش پ 379395",
      "deposit": 0.0,
      "withdrawal": 7840000.0,
      "balance": 1008875304.0,
      "source_page": 51,
      "row_order": 44
    },
    {
      "date": "1405/01/21",
      "time": "15:24:26",
      "description": "برداشت از سپرده بابت کارمزد انتقال کارت به کارت-تراکنش اصلی ش م 177582206616 ش پ 962261",
      "deposit": 0.0,
      "withdrawal": 12200.0,
      "balance": 1016715304.0,
      "source_page": 51,
      "row_order": 45
    },
    {
      "date": "1405/01/21",
      "time": "15:24:26",
      "description": "انتقال به کارت شماره: ****-****-****-**** بنام: فرهاد ملکی از درگاه اینترنتی بانک سامان 10000006 - ش م: 177582206616 ش پ: 962261",
      "deposit": 0.0,
      "withdrawal": 12000000.0,
      "balance": 1016727504.0,
      "source_page": 51,
      "row_order": 46
    },
    {
      "date": "1405/01/21",
      "time": "10:51:18",
      "description": "خرید کالا و خدمات از پایانه فروش 12263942 نوین پرداخت آرین ش م 515764460288 ش پ 805413",
      "deposit": 0.0,
      "withdrawal": 3800000.0,
      "balance": 1028727504.0,
      "source_page": 51,
      "row_order": 47
    },
    {
      "date": "1405/01/21",
      "time": "09:08:36",
      "description": "خرید کالا و خدمات از پایانه فروش 12544840 پرداخت الکترونیک سامان ش م 860389092951 ش پ 206407",
      "deposit": 0.0,
      "withdrawal": 1700000.0,
      "balance": 1032527504.0,
      "source_page": 51,
      "row_order": 48
    },
    {
      "date": "1405/01/20",
      "time": "16:14:31",
      "description": "انتقال به سپرده بلو - شماره سپرده: 611828005577607501 بنام: امین صدقیان - شماره سند: 1405403454026",
      "deposit": 0.0,
      "withdrawal": 18000000.0,
      "balance": 1034227504.0,
      "source_page": 51,
      "row_order": 49
    },
    {
      "date": "1405/01/20",
      "time": "15:17:41",
      "description": "برداشت از سپرده بابت کارمزد انتقال پل - کد پیگیری تراکنش اصلی: 1405012005631515174178410",
      "deposit": 0.0,
      "withdrawal": 16000.0,
      "balance": 1052227504.0,
      "source_page": 51,
      "row_order": 50
    },
    {
      "date": "1405/01/20",
      "time": "15:17:41",
      "description": "انتقال پل به شماره شبا IR210120010000009189773545 بانک ملت بنام شیما طایفه - کد پیگیری تراکنش: 1405012005631515174178410",
      "deposit": 0.0,
      "withdrawal": 80000000.0,
      "balance": 1052243504.0,
      "source_page": 51,
      "row_order": 51
    },
    {
      "date": "1405/01/20",
      "time": "13:55:34",
      "description": "برداشت از سپرده بابت کارمزد انتقال پل - کد پیگیری تراکنش اصلی: 1405012005631513553480710",
      "deposit": 0.0,
      "withdrawal": 14000.0,
      "balance": 1132243504.0,
      "source_page": 51,
      "row_order": 52
    },
    {
      "date": "1405/01/20",
      "time": "13:55:34",
      "description": "انتقال پل به شماره شبا IR210120010000009189773545 بانک ملت بنام شیما طایفه - کد پیگیری تراکنش: 1405012005631513553480710",
      "deposit": 0.0,
      "withdrawal": 70000000.0,
      "balance": 1132257504.0,
      "source_page": 51,
      "row_order": 53
    },
    {
      "date": "1405/01/20",
      "time": "13:55:10",
      "description": "برداشت از سپرده بابت کارمزد انتقال کارت به کارت-تراکنش اصلی ش م 177573030988 ش پ 697014",
      "deposit": 0.0,
      "withdrawal": 34600.0,
      "balance": 1202257504.0,
      "source_page": 51,
      "row_order": 54
    },
    {
      "date": "1405/01/20",
      "time": "13:55:10",
      "description": "انتقال به کارت شماره: ****-****-****-**** بنام: حامد نامداری از درگاه اینترنتی بانک سامان 10000006 - ش م: 177573030988 ش پ: 697014",
      "deposit": 0.0,
      "withdrawal": 84000000.0,
      "balance": 1202292104.0,
      "source_page": 51,
      "row_order": 55
    },
    {
      "date": "1405/01/20",
      "time": "13:54:29",
      "description": "انتقال به سپرده بلو - شماره سپرده: 611828005383885701 بنام: محمد دهقان - شماره سند: 1405400539459",
      "deposit": 0.0,
      "withdrawal": 130000000.0,
      "balance": 1286292104.0,
      "source_page": 51,
      "row_order": 56
    },
    {
      "date": "1405/01/19",
      "time": "16:51:25",
      "description": "خرید کالا و خدمات از پایانه فروش 08940986 به پرداخت ملت ش م 341423866206 ش پ 866206",
      "deposit": 0.0,
      "withdrawal": 900000.0,
      "balance": 1416292104.0,
      "source_page": 51,
      "row_order": 57
    },
    {
      "date": "1405/01/19",
      "time": "16:21:00",
      "description": "برداشت از سپرده بابت کارمزد انتقال پل - کد پیگیری تراکنش اصلی: 1405011905635616210084110",
      "deposit": 0.0,
      "withdrawal": 7000.0,
      "balance": 1417192104.0,
      "source_page": 51,
      "row_order": 58
    },
    {
      "date": "1405/01/19",
      "time": "16:21:00",
      "description": "انتقال پل به شماره شبا IR860140040000310041871065 بانک مسکن بنام سارا کشاورزپاک سرشت - کد پیگیری تراکنش: 1405011905635616210084110",
      "deposit": 0.0,
      "withdrawal": 35000000.0,
      "balance": 1417199104.0,
      "source_page": 51,
      "row_order": 59
    },
    {
      "date": "1405/01/19",
      "time": "15:24:51",
      "description": "برداشت از سپرده بابت کارمزد انتقال پل - کد پیگیری تراکنش اصلی: 1405011905635615245163810",
      "deposit": 0.0,
      "withdrawal": 16000.0,
      "balance": 1452199104.0,
      "source_page": 51,
      "row_order": 60
    },
    {
      "date": "1405/01/19",
      "time": "15:24:51",
      "description": "انتقال پل به شماره شبا IR650210000001000214749060 پست بانک بنام معصومه نوروزی - کد پیگیری تراکنش: 1405011905635615245163810",
      "deposit": 0.0,
      "withdrawal": 80000000.0,
      "balance": 1452215104.0,
      "source_page": 51,
      "row_order": 61
    },
    {
      "date": "1405/01/19",
      "time": "13:53:23",
      "description": "خرید کالا و خدمات از پایانه فروش 14428213 پرداخت الکترونیک سامان ش م 860338255383 ش پ 693839",
      "deposit": 0.0,
      "withdrawal": 25000000.0,
      "balance": 1532215104.0,
      "source_page": 51,
      "row_order": 62
    },
    {
      "date": "1405/01/19",
      "time": "13:47:14",
      "description": "خرید کالا و خدمات از پایانه فروش 07442387 به پرداخت ملت ش م 341409250340 ش پ 250340",
      "deposit": 0.0,
      "withdrawal": 5000000.0,
      "balance": 1557215104.0,
      "source_page": 51,
      "row_order": 63
    },
    {
      "date": "1405/01/19",
      "time": "12:59:59",
      "description": "انتقال به سپرده بلو - شماره سپرده: 611828005477639001 بنام: محسن کریمی - شماره سند: 1405376018253",
      "deposit": 0.0,
      "withdrawal": 57000000.0,
      "balance": 1562215104.0,
      "source_page": 51,
      "row_order": 64
    },
    {
      "date": "1405/01/19",
      "time": "12:55:00",
      "description": "انتقال از سپرده بلو - شماره سپرده: 611828005245270001 بنام: امیرحسین مایلی قلقلوئی - شماره سند: 1405375891282",
      "deposit": 140000000.0,
      "withdrawal": 0.0,
      "balance": 1619215104.0,
      "source_page": 51,
      "row_order": 65
    },
    {
      "date": "1405/01/19",
      "time": "11:26:51",
      "description": "برداشت از سپرده بابت کارمزد انتقال کارت به کارت-تراکنش اصلی ش م 177563501091 ش پ 864405",
      "deposit": 0.0,
      "withdrawal": 12200.0,
      "balance": 1479215104.0,
      "source_page": 51,
      "row_order": 66
    },
    {
      "date": "1405/01/19",
      "time": "11:26:51",
      "description": "انتقال به کارت شماره: ****-****-****-**** بنام: داود هادی زاده از درگاه اینترنتی بانک سامان 10000006 - ش م: 177563501091 ش پ: 864405",
      "deposit": 0.0,
      "withdrawal": 20000000.0,
      "balance": 1479227304.0,
      "source_page": 51,
      "row_order": 67
    },
    {
      "date": "1405/01/19",
      "time": "11:20:01",
      "description": "برداشت از سپرده بابت کارمزد انتقال کارت به کارت-تراکنش اصلی ش م 177563460105 ش پ 514364",
      "deposit": 0.0,
      "withdrawal": 28200.0,
      "balance": 1499227304.0,
      "source_page": 51,
      "row_order": 68
    },
    {
      "date": "1405/01/19",
      "time": "11:20:01",
      "description": "انتقال به کارت شماره: ****-****-****-**** بنام: سیدمحمدحسین حسینی خواه از درگاه اینترنتی بانک سامان 10000006 - ش م: 177563460105 ش پ: 514364",
      "deposit": 0.0,
      "withdrawal": 63600000.0,
      "balance": 1499255504.0,
      "source_page": 51,
      "row_order": 69
    },
    {
      "date": "1405/01/19",
      "time": "01:12:37",
      "description": "برداشت بابت خرید شارژ ایرانسل - شماره تلفن 09371579532 ش م: 1153358901 ش پ: ****-****-****-****",
      "deposit": 0.0,
      "withdrawal": 550000.0,
      "balance": 1562855504.0,
      "source_page": 51,
      "row_order": 70
    },
    {
      "date": "1405/01/18",
      "time": "22:04:38",
      "description": "برداشت از سپرده بابت کارمزد انتقال پل - کد پیگیری تراکنش اصلی: 1405011805635922043822110",
      "deposit": 0.0,
      "withdrawal": 5000.0,
      "balance": 1563405504.0,
      "source_page": 51,
      "row_order": 71
    },
    {
      "date": "1405/01/18",
      "time": "22:04:38",
      "description": "انتقال پل به شماره شبا IR460170000000224238232006 بانک ملی بنام زهره جمشیدی دیپیجانی - کد پیگیری تراکنش: 1405011805635922043822110",
      "deposit": 0.0,
      "withdrawal": 5000000.0,
      "balance": 1563410504.0,
      "source_page": 51,
      "row_order": 72
    },
    {
      "date": "1405/01/18",
      "time": "21:09:35",
      "description": "برداشت از سپرده بابت کارمزد انتقال پل - کد پیگیری تراکنش اصلی: 1405011805636721093573610",
      "deposit": 0.0,
      "withdrawal": 12000.0,
      "balance": 1568410504.0,
      "source_page": 51,
      "row_order": 73
    },
    {
      "date": "1405/01/18",
      "time": "21:09:35",
      "description": "انتقال پل به شماره شبا IR820120010000004289595123 بانک ملت بنام فرزاد آقاخانی - کد پیگیری تراکنش: 1405011805636721093573610",
      "deposit": 0.0,
      "withdrawal": 60000000.0,
      "balance": 1568422504.0,
      "source_page": 51,
      "row_order": 74
    },
    {
      "date": "1405/01/18",
      "time": "16:13:55",
      "description": "خرید کالا و خدمات از پایانه فروش 54311629 تجارت الکترونیک پارسیان ش م 812421408024 ش پ 758155",
      "deposit": 0.0,
      "withdrawal": 8000000.0,
      "balance": 1628422504.0,
      "source_page": 51,
      "row_order": 75
    },
    {
      "date": "1405/01/18",
      "time": "16:09:11",
      "description": "خرید کالا و خدمات از پایانه فروش 13996123 پرداخت الکترونیک سامان ش م 860311814220 ش پ 357676",
      "deposit": 0.0,
      "withdrawal": 26500000.0,
      "balance": 1636422504.0,
      "source_page": 51,
      "row_order": 76
    },
    {
      "date": "1405/01/18",
      "time": "15:14:12",
      "description": "خرید کالا و خدمات از پایانه فروش 12696860 پرداخت الکترونیک سامان ش م 860310535035 ش پ 898491",
      "deposit": 0.0,
      "withdrawal": 100000000.0,
      "balance": 1662922504.0,
      "source_page": 51,
      "row_order": 77
    },
    {
      "date": "1405/01/18",
      "time": "13:21:37",
      "description": "برداشت از سپرده بابت کارمزد انتقال کارت به کارت-تراکنش اصلی ش م 177555549662 ش پ 514816",
      "deposit": 0.0,
      "withdrawal": 37800.0,
      "balance": 1762922504.0,
      "source_page": 51,
      "row_order": 78
    },
    {
      "date": "1405/01/18",
      "time": "13:21:37",
      "description": "انتقال به کارت شماره: ****-****-****-**** بنام: شیما طایفه از درگاه اینترنتی بانک سامان 10000006 - ش م: 177555549662 ش پ: 514816",
      "deposit": 0.0,
      "withdrawal": 100000000.0,
      "balance": 1762960304.0,
      "source_page": 51,
      "row_order": 79
    },
    {
      "date": "1405/01/18",
      "time": "13:20:44",
      "description": "برداشت از سپرده بابت کارمزد انتقال پل - کد پیگیری تراکنش اصلی: 1405011805635913204456110",
      "deposit": 0.0,
      "withdrawal": 63700.0,
      "balance": 1862960304.0,
      "source_page": 51,
      "row_order": 80
    },
    {
      "date": "1405/01/18",
      "time": "13:20:44",
      "description": "انتقال پل به شماره شبا IR580780202010020001051556 بانک خاورمیانه بنام حمید نادمی اردستانی - کد پیگیری تراکنش: 1405011805635913204456110",
      "deposit": 0.0,
      "withdrawal": 318500000.0,
      "balance": 1863024004.0,
      "source_page": 51,
      "row_order": 81
    },
    {
      "date": "1405/01/18",
      "time": "13:17:19",
      "description": "انتقال از کارت شماره: ****-****-****-**** بنام: محدثه نوری از درگاه اینترنتی بانک کشاورزی 07770023 - ش م: 040713899402 ش پ: 899402",
      "deposit": 16000000.0,
      "withdrawal": 0.0,
      "balance": 2181524004.0,
      "source_page": 51,
      "row_order": 82
    },
    {
      "date": "1405/01/18",
      "time": "13:16:02",
      "description": "برداشت از سپرده بابت کارمزد انتقال پایا - شماره پیگیری تراکنش اصلی 140501180562829476",
      "deposit": 0.0,
      "withdrawal": 28850.0,
      "balance": 2165524004.0,
      "source_page": 51,
      "row_order": 83
    },
    {
      "date": "1405/01/18",
      "time": "13:16:02",
      "description": "انتقال پایا به شماره شبا IR150700001000115476190001 بانک قرض الحسنه رسالت بنام: حامد نامداری - شماره پیگیری تراکنش: 140501180562829476",
      "deposit": 0.0,
      "withdrawal": 288500000.0,
      "balance": 2165552854.0,
      "source_page": 51,
      "row_order": 84
    },
    {
      "date": "1405/01/18",
      "time": "13:14:48",
      "description": "انتقال به سپرده بلو - شماره سپرده: 611828005383885701 بنام: محمد دهقان - شماره سند: 1405353361356",
      "deposit": 0.0,
      "withdrawal": 183500000.0,
      "balance": 2454052854.0,
      "source_page": 51,
      "row_order": 85
    },
    {
      "date": "1405/01/18",
      "time": "09:01:32",
      "description": "واریز سود علی الحساب به 611828005736340901 از تاریخ: 18-12-1404 تا تاریخ: 18-01-1405 - شماره سند: 1405347730467",
      "deposit": 40912.0,
      "withdrawal": 0.0,
      "balance": 2637552854.0,
      "source_page": 51,
      "row_order": 86
    },
    {
      "date": "1405/01/18",
      "time": "08:50:00",
      "description": "انتقال ساتنا از شماره شبا IR060120000000009773322482 بانک ملت بنام: سیدمحمود سیدی - شماره مرجع تراکنش: ****-****-****-****",
      "deposit": 1000000000.0,
      "withdrawal": 0.0,
      "balance": 2637511942.0,
      "source_page": 51,
      "row_order": 87
    },
    {
      "date": "1405/01/18",
      "time": "04:44:18",
      "description": "انتقال پایا از شماره شبا IR510580102271302446716001 بانک سرمایه بنام: صمد آزادمردفرد - شماره پیگیری تراکنش: 14050117058206346505",
      "deposit": 1500000000.0,
      "withdrawal": 0.0,
      "balance": 1637511942.0,
      "source_page": 51,
      "row_order": 88
    },
    {
      "date": "1405/01/17",
      "time": "20:57:27",
      "description": "انتقال به سپرده بلو - شماره سپرده: 611828005221264601 بنام: امید آریافرد - شماره سند: 1405341675928",
      "deposit": 0.0,
      "withdrawal": 25000000.0,
      "balance": 137511942.0,
      "source_page": 51,
      "row_order": 89
    },
    {
      "date": "1405/01/17",
      "time": "12:02:51",
      "description": "انتقال از سپرده بلو - شماره سپرده: 611828007082983201 بنام: هانیه پوری - شماره سند: 1405328366101",
      "deposit": 750000000.0,
      "withdrawal": 0.0,
      "balance": 162511942.0,
      "source_page": 51,
      "row_order": 90
    },
    {
      "date": "1405/01/16",
      "time": "17:39:29",
      "description": "برداشت از سپرده بابت کارمزد انتقال کارت به کارت-تراکنش اصلی ش م 177539816873 ش پ 345466",
      "deposit": 0.0,
      "withdrawal": 12200.0,
      "balance": 87511942.0,
      "source_page": 51,
      "row_order": 91
    },
    {
      "date": "1405/01/16",
      "time": "17:39:29",
      "description": "انتقال به کارت شماره: ****-****-****-**** بنام: فرهاد ملکی از درگاه اینترنتی بانک سامان 10000006 - ش م: 177539816873 ش پ: 345466",
      "deposit": 0.0,
      "withdrawal": 12000000.0,
      "balance": 87524142.0,
      "source_page": 51,
      "row_order": 92
    },
    {
      "date": "1405/01/16",
      "time": "08:56:17",
      "description": "خرید کالا و خدمات از پایانه فروش 99205232 تجارت الکترونیک پارسیان ش م 812400235225 ش پ 572849",
      "deposit": 0.0,
      "withdrawal": 1650000.0,
      "balance": 99524142.0,
      "source_page": 51,
      "row_order": 93
    },
    {
      "date": "1405/01/16",
      "time": "00:03:29",
      "description": "برداشت از سپرده بابت کارمزد انتقال کارت به کارت-تراکنش اصلی ش م 175959169281 ش پ 169281",
      "deposit": 0.0,
      "withdrawal": 9000.0,
      "balance": 101174142.0,
      "source_page": 51,
      "row_order": 94
    },
    {
      "date": "1405/01/16",
      "time": "00:03:29",
      "description": "انتقال به کارت شماره: ****-****-****-**** بنام: عیوض کاظمی حاج سیران از کیوسک 21468265 بانک ملت - ش م: 175959169281 ش پ: 169281",
      "deposit": 0.0,
      "withdrawal": 4800000.0,
      "balance": 101183142.0,
      "source_page": 51,
      "row_order": 95
    },
    {
      "date": "1405/01/15",
      "time": "16:12:59",
      "description": "برداشت از سپرده بابت کارمزد انتقال کارت به کارت-تراکنش اصلی ش م 177530657840 ش پ 884179",
      "deposit": 0.0,
      "withdrawal": 9000.0,
      "balance": 105983142.0,
      "source_page": 51,
      "row_order": 96
    },
    {
      "date": "1405/01/15",
      "time": "16:12:59",
      "description": "انتقال به کارت شماره: ****-****-****-**** بنام: شهناز بازرگانی از درگاه اینترنتی بانک سامان 10000006 - ش م: 177530657840 ش پ: 884179",
      "deposit": 0.0,
      "withdrawal": 10000000.0,
      "balance": 105992142.0,
      "source_page": 51,
      "row_order": 97
    },
    {
      "date": "1405/01/14",
      "time": "19:43:59",
      "description": "برداشت از سپرده بابت کارمزد انتقال کارت به کارت-تراکنش اصلی ش م 177523283911 ش پ 323000",
      "deposit": 0.0,
      "withdrawal": 9000.0,
      "balance": 115992142.0,
      "source_page": 51,
      "row_order": 98
    },
    {
      "date": "1405/01/14",
      "time": "19:43:59",
      "description": "انتقال به کارت شماره: ****-****-****-**** بنام: فرهاد ملکی از درگاه اینترنتی بانک سامان 10000006 - ش م: 177523283911 ش پ: 323000",
      "deposit": 0.0,
      "withdrawal": 6000000.0,
      "balance": 116001142.0,
      "source_page": 51,
      "row_order": 99
    },
    {
      "date": "1405/01/14",
      "time": "17:58:17",
      "description": "برداشت از سپرده بابت کارمزد انتقال کارت به کارت-تراکنش اصلی ش م 177522649665 ش پ 739856",
      "deposit": 0.0,
      "withdrawal": 9000.0,
      "balance": 122001142.0,
      "source_page": 51,
      "row_order": 100
    },
    {
      "date": "1405/01/14",
      "time": "17:58:17",
      "description": "انتقال به کارت شماره: ****-****-****-**** بنام: سعید اسدی از درگاه اینترنتی بانک سامان 10000006 - ش م: 177522649665 ش پ: 739856",
      "deposit": 0.0,
      "withdrawal": 5000000.0,
      "balance": 122010142.0,
      "source_page": 51,
      "row_order": 101
    },
    {
      "date": "1405/01/14",
      "time": "15:27:55",
      "description": "برداشت از سپرده بابت کارمزد انتقال کارت به کارت-تراکنش اصلی ش م 177521747501 ش پ 612546",
      "deposit": 0.0,
      "withdrawal": 12200.0,
      "balance": 127010142.0,
      "source_page": 51,
      "row_order": 102
    },
    {
      "date": "1405/01/14",
      "time": "15:27:55",
      "description": "انتقال به کارت شماره: ****-****-****-**** بنام: فریدون الماسی از درگاه اینترنتی بانک سامان 10000006 - ش م: 177521747501 ش پ: 612546",
      "deposit": 0.0,
      "withdrawal": 20000000.0,
      "balance": 127022342.0,
      "source_page": 51,
      "row_order": 103
    },
    {
      "date": "1405/01/14",
      "time": "15:10:26",
      "description": "انتقال به سپرده بلو - شماره سپرده: 611828005139942801 بنام: محمدمهدی رخدادیان - شماره سند: 1405264663042",
      "deposit": 0.0,
      "withdrawal": 9400000.0,
      "balance": 147022342.0,
      "source_page": 51,
      "row_order": 104
    },
    {
      "date": "1405/01/13",
      "time": "14:33:36",
      "description": "برداشت از سپرده بابت کارمزد انتقال کارت به کارت-تراکنش اصلی ش م 177512781632 ش پ 108626",
      "deposit": 0.0,
      "withdrawal": 12200.0,
      "balance": 156422342.0,
      "source_page": 51,
      "row_order": 105
    },
    {
      "date": "1405/01/13",
      "time": "14:33:36",
      "description": "انتقال به کارت شماره: ****-****-****-**** بنام: حسن قنبریان از درگاه اینترنتی بانک سامان 10000006 - ش م: 177512781632 ش پ: 108626",
      "deposit": 0.0,
      "withdrawal": 12000000.0,
      "balance": 156434542.0,
      "source_page": 51,
      "row_order": 106
    },
    {
      "date": "1405/01/12",
      "time": "23:11:53",
      "description": "برداشت از سپرده بابت کارمزد انتقال کارت به کارت-تراکنش اصلی ش م 177507251317 ش پ 113402",
      "deposit": 0.0,
      "withdrawal": 9000.0,
      "balance": 168434542.0,
      "source_page": 51,
      "row_order": 107
    },
    {
      "date": "1405/01/12",
      "time": "23:11:53",
      "description": "انتقال به کارت شماره: ****-****-****-**** بنام: سیدجلال حسینی از درگاه اینترنتی بانک سامان 10000006 - ش م: 177507251317 ش پ: 113402",
      "deposit": 0.0,
      "withdrawal": 5000000.0,
      "balance": 168443542.0,
      "source_page": 51,
      "row_order": 108
    },
    {
      "date": "1405/01/12",
      "time": "15:41:03",
      "description": "برداشت از سپرده بابت کارمزد انتقال کارت به کارت-تراکنش اصلی ش م 177504546319 ش پ 286863",
      "deposit": 0.0,
      "withdrawal": 9000.0,
      "balance": 173443542.0,
      "source_page": 51,
      "row_order": 109
    },
    {
      "date": "1405/01/12",
      "time": "15:41:03",
      "description": "انتقال به کارت شماره: ****-****-****-**** بنام: مسعود دینارگرگویچ از درگاه اینترنتی بانک سامان 10000006 - ش م: 177504546319 ش پ: 286863",
      "deposit": 0.0,
      "withdrawal": 10000000.0,
      "balance": 173452542.0,
      "source_page": 51,
      "row_order": 110
    },
    {
      "date": "1405/01/12",
      "time": "10:35:26",
      "description": "انتقال به سپرده بلو - شماره سپرده: 611828005590715601 بنام: مهدی نصیری کامران - شماره سند: 1405226021645",
      "deposit": 0.0,
      "withdrawal": 17000000.0,
      "balance": 183452542.0,
      "source_page": 51,
      "row_order": 111
    },
    {
      "date": "1405/01/12",
      "time": "08:54:06",
      "description": "برداشت از سپرده بابت کارمزد انتقال کارت به کارت-تراکنش اصلی ش م 177502104554 ش پ 412817",
      "deposit": 0.0,
      "withdrawal": 21800.0,
      "balance": 200452542.0,
      "source_page": 51,
      "row_order": 112
    },
    {
      "date": "1405/01/12",
      "time": "08:54:06",
      "description": "انتقال به کارت شماره: ****-****-****-**** بنام: دیانا سلطانی از درگاه اینترنتی بانک سامان 10000006 - ش م: 177502104554 ش پ: 412817",
      "deposit": 0.0,
      "withdrawal": 50000000.0,
      "balance": 200474342.0,
      "source_page": 51,
      "row_order": 113
    },
    {
      "date": "1405/01/12",
      "time": "08:53:32",
      "description": "برداشت از سپرده بابت کارمزد انتقال کارت به کارت-تراکنش اصلی ش م 177502101163 ش پ 277264",
      "deposit": 0.0,
      "withdrawal": 18600.0,
      "balance": 250474342.0,
      "source_page": 51,
      "row_order": 114
    },
    {
      "date": "1405/01/12",
      "time": "08:53:32",
      "description": "انتقال به کارت شماره: ****-****-****-**** بنام: دیانا سلطانی از درگاه اینترنتی بانک سامان 10000006 - ش م: 177502101163 ش پ: 277264",
      "deposit": 0.0,
      "withdrawal": 35000000.0,
      "balance": 250492942.0,
      "source_page": 51,
      "row_order": 115
    },
    {
      "date": "1405/01/11",
      "time": "12:40:19",
      "description": "انتقال پل از شماره شبا IR040170000000373351530001 بانک ملی بنام حاتمی - کد پیگیری تراکنش: 140501110173956694659124018 - بهزاد",
      "deposit": 55000000.0,
      "withdrawal": 0.0,
      "balance": 285492942.0,
      "source_page": 51,
      "row_order": 116
    },
    {
      "date": "1405/01/11",
      "time": "11:53:18",
      "description": "انتقال پل از شماره شبا IR040170000000373351530001 بانک ملی بنام حاتمی - کد پیگیری تراکنش: 140501110173440283835115317 - بهزاد",
      "deposit": 170000000.0,
      "withdrawal": 0.0,
      "balance": 230492942.0,
      "source_page": 51,
      "row_order": 117
    },
    {
      "date": "1405/01/10",
      "time": "17:11:46",
      "description": "انتقال از سپرده بلو - شماره سپرده: 611828005664802901 بنام: فاطمه کاوسی - شماره سند: 1405192588548",
      "deposit": 7000000.0,
      "withdrawal": 0.0,
      "balance": 60492942.0,
      "source_page": 51,
      "row_order": 118
    },
    {
      "date": "1405/01/10",
      "time": "15:29:49",
      "description": "انتقال از کارت شماره: ****-****-****-**** بنام: امید عابدین زاده پزوه از درگاه اینترنتی بانک مسکن 09999420 - ش م: 000000947962 ش پ: 492664",
      "deposit": 25000000.0,
      "withdrawal": 0.0,
      "balance": 53492942.0,
      "source_page": 51,
      "row_order": 119
    },
    {
      "date": "1405/01/10",
      "time": "13:42:09",
      "description": "انتقال به سپرده بلو - شماره سپرده: 611828005707107501 بنام: امیررضا عطاردی - شماره سند: 1405188477632",
      "deposit": 0.0,
      "withdrawal": 1000000.0,
      "balance": 28492942.0,
      "source_page": 51,
      "row_order": 120
    },
    {
      "date": "1405/01/10",
      "time": "13:05:14",
      "description": "برداشت از سپرده بابت کارمزد انتقال کارت به کارت-تراکنش اصلی ش م 177486331387 ش پ 836930",
      "deposit": 0.0,
      "withdrawal": 9000.0,
      "balance": 29492942.0,
      "source_page": 51,
      "row_order": 121
    },
    {
      "date": "1405/01/10",
      "time": "13:05:14",
      "description": "انتقال به کارت شماره: ****-****-****-**** بنام: سیدمحمدمهدی فقیه زاده فیروزآبادی از درگاه اینترنتی بانک سامان 10000006 - ش م: 177486331387 ش پ: 836930",
      "deposit": 0.0,
      "withdrawal": 3500000.0,
      "balance": 29501942.0,
      "source_page": 51,
      "row_order": 122
    },
    {
      "date": "1405/01/09",
      "time": "18:12:07",
      "description": "برداشت از سپرده بابت کارمزد انتقال کارت به کارت-تراکنش اصلی ش م 177479532699 ش پ 961282",
      "deposit": 0.0,
      "withdrawal": 12200.0,
      "balance": 33001942.0,
      "source_page": 51,
      "row_order": 123
    },
    {
      "date": "1405/01/09",
      "time": "18:12:07",
      "description": "انتقال به کارت شماره: ****-****-****-**** بنام: فرهاد ملکی از درگاه اینترنتی بانک سامان 10000006 - ش م: 177479532699 ش پ: 961282",
      "deposit": 0.0,
      "withdrawal": 12000000.0,
      "balance": 33014142.0,
      "source_page": 51,
      "row_order": 124
    },
    {
      "date": "1405/01/09",
      "time": "11:30:06",
      "description": "خرید کالا و خدمات از پایانه فروش 99394522 تجارت الکترونیک پارسیان ش م 812349925497 ش پ 249031",
      "deposit": 0.0,
      "withdrawal": 1400000.0,
      "balance": 45014142.0,
      "source_page": 51,
      "row_order": 125
    },
    {
      "date": "1405/01/08",
      "time": "16:46:33",
      "description": "خرید کالا و خدمات از پایانه فروش 08979741 به پرداخت ملت ش م 340405649934 ش پ 649934",
      "deposit": 0.0,
      "withdrawal": 750000.0,
      "balance": 46414142.0,
      "source_page": 51,
      "row_order": 126
    },
    {
      "date": "1405/01/08",
      "time": "12:28:43",
      "description": "انتقال از کارت شماره: ****-****-****-**** بنام: میلاد عفتی از درگاه اینترنتی بانک ملی ایران 17592030 - ش م: 341652576270 ش پ: 402082",
      "deposit": 30000000.0,
      "withdrawal": 0.0,
      "balance": 47164142.0,
      "source_page": 51,
      "row_order": 127
    },
    {
      "date": "1405/01/08",
      "time": "12:24:09",
      "description": "برداشت از سپرده بابت کارمزد استعلام موجودی کارت - از پایانه فروشگاهی کارت اعتباری ایران کیش 07406632 ش م 066320860245 ش پ 000477",
      "deposit": 0.0,
      "withdrawal": 1800.0,
      "balance": 17164142.0,
      "source_page": 51,
      "row_order": 128
    },
    {
      "date": "1405/01/04",
      "time": "18:39:30",
      "description": "برداشت از سپرده بابت کارمزد انتقال کارت به کارت-تراکنش اصلی ش م 177436496991 ش پ 564597",
      "deposit": 0.0,
      "withdrawal": 9000.0,
      "balance": 17165942.0,
      "source_page": 51,
      "row_order": 129
    },
    {
      "date": "1405/01/04",
      "time": "18:39:30",
      "description": "انتقال به کارت شماره: ****-****-****-**** بنام: بانک سامان 10000006 از درگاه اینترنتی - ش م: 177436496991 ش پ: 564597",
      "deposit": 0.0,
      "withdrawal": 3000000.0,
      "balance": 17174942.0,
      "source_page": 51,
      "row_order": 130
    },
    {
      "date": "1405/01/02",
      "time": "09:56:07",
      "description": "خرید کالا و خدمات از پایانه فروش 09008051 به پرداخت ملت ش م 339855936545 ش پ 936545",
      "deposit": 0.0,
      "withdrawal": 880000.0,
      "balance": 20174942.0,
      "source_page": 51,
      "row_order": 131
    },
    {
      "date": "1405/01/01",
      "time": "13:03:03",
      "description": "خرید کالا و خدمات از پایانه فروش 99205232 تجارت الکترونیک پارسیان ش م 812295617957 ش پ 925203",
      "deposit": 0.0,
      "withdrawal": 1800000.0,
      "balance": 21054942.0,
      "source_page": 51,
      "row_order": 132
    },
    {
      "date": "1404/12/29",
      "time": "13:04:24",
      "description": "برداشت از سپرده بابت کارمزد انتقال کارت به کارت-تراکنش اصلی ش م 177399926404 ش پ 946727",
      "deposit": 0.0,
      "withdrawal": 9000.0,
      "balance": 22854942.0,
      "source_page": 51,
      "row_order": 133
    },
    {
      "date": "1404/12/29",
      "time": "13:04:24",
      "description": "انتقال به کارت شماره: ****-****-****-**** بنام: کاظم نجاتی شارک از درگاه اینترنتی بانک سامان 10000006 - ش م: 177399926404 ش پ: 946727",
      "deposit": 0.0,
      "withdrawal": 1000000.0,
      "balance": 22863942.0,
      "source_page": 51,
      "row_order": 134
    },
    {
      "date": "1404/12/29",
      "time": "11:48:23",
      "description": "برداشت از سپرده بابت کارمزد انتقال کارت به کارت-تراکنش اصلی ش م 177399470276 ش پ 639415",
      "deposit": 0.0,
      "withdrawal": 9000.0,
      "balance": 23863942.0,
      "source_page": 51,
      "row_order": 135
    },
    {
      "date": "1404/12/29",
      "time": "11:48:23",
      "description": "انتقال به کارت شماره: ****-****-****-**** بنام: نسترن سادات میرهاشمی از درگاه اینترنتی بانک سامان 10000006 - ش م: 177399470276 ش پ: 639415",
      "deposit": 0.0,
      "withdrawal": 10000000.0,
      "balance": 23872942.0,
      "source_page": 51,
      "row_order": 136
    },
    {
      "date": "1404/12/29",
      "time": "10:35:24",
      "description": "انتقال به سپرده بلو - شماره سپرده: 611828005743524401 بنام: مهدی دهقان نیری - شماره سند: 14046569591678",
      "deposit": 0.0,
      "withdrawal": 7000000.0,
      "balance": 33872942.0,
      "source_page": 51,
      "row_order": 137
    },
    {
      "date": "1404/12/28",
      "time": "16:14:47",
      "description": "خرید کالا و خدمات از پایانه فروش 44959092 تجارت الکترونیک پارسیان ش م 749696058676 ش پ 893677",
      "deposit": 0.0,
      "withdrawal": 900000.0,
      "balance": 40872942.0,
      "source_page": 51,
      "row_order": 138
    },
    {
      "date": "1404/12/27",
      "time": "22:14:29",
      "description": "انتقال به سپرده بلو - شماره سپرده: 611828006379962602 بنام: مهدی اعیان منش راد - شماره سند: 14046533386169",
      "deposit": 0.0,
      "withdrawal": 14000000.0,
      "balance": 41772942.0,
      "source_page": 51,
      "row_order": 139
    }
  ],
  "extraction_status": "ok",
  "notes": null
}