{
  "page_number": 35,
  "account_holder_name": null,
  "transactions": [
    {
      "date": "1405/02/07",
      "time": "12:47:35",
      "description": "1405020705634412473530310 برداشت از سپرده بابت کارمزد انتقال پل: - کد پیگیری تراکنش اصلی:",
      "deposit": 0.0,
      "withdrawal": 20000.0,
      "balance": 831729394.0,
      "source_page": 35,
      "row_order": 1
    },
    {
      "date": "1405/02/07",
      "time": "12:47:35",
      "description": "حمیدرضا کاظمی - کد پیگیری تراکنش: 1405020705634412473530310 انتقال پل به شماره شبا: IR450120000000005595294324 بانک ملت بنام",
      "deposit": 0.0,
      "withdrawal": 100000000.0,
      "balance": 831749394.0,
      "source_page": 35,
      "row_order": 2
    },
    {
      "date": "1405/02/07",
      "time": "11:31:38",
      "description": "ش م 142051286747 ش پ 000072 خرید کالا و خدمات از پایانه فروش 70680590 ۲ پرداخت الکترونیک پاسارگاد",
      "deposit": 0.0,
      "withdrawal": 20000000.0,
      "balance": 931749394.0,
      "source_page": 35,
      "row_order": 3
    },
    {
      "date": "1405/02/07",
      "time": "10:14:08",
      "description": "812591315972 ش پ 747177 خرید کالا و خدمات از پایانه فروش 93090837 تجارت الکترونیک پارسیان ش م",
      "deposit": 0.0,
      "withdrawal": 640000.0,
      "balance": 951749394.0,
      "source_page": 35,
      "row_order": 4
    },
    {
      "date": "1405/02/07",
      "time": "08:56:47",
      "description": "177726760673 ش پ 552506 برداشت از سپرده بابت کارمزد انتقال کارت به کارت-تراکنش اصلی ش م",
      "deposit": 0.0,
      "withdrawal": 9000.0,
      "balance": 952389394.0,
      "source_page": 35,
      "row_order": 5
    },
    {
      "date": "1405/02/07",
      "time": "08:56:47",
      "description": "اینترنتی 10000006 بانک سامان - ش م: 177726760673 ش پ: 552506 انتقال به کارت شماره: 5859831074499178 بنام: بهمن میرزائی از درگاه",
      "deposit": 0.0,
      "withdrawal": 3440000.0,
      "balance": 952398394.0,
      "source_page": 35,
      "row_order": 6
    },
    {
      "date": "1405/02/06",
      "time": "20:32:17",
      "description": "860884181884 ش پ 250340 خرید کالا و خدمات از پایانه فروش 11695088 پرداخت الکترونیک سامان ش م",
      "deposit": 0.0,
      "withdrawal": 3000000.0,
      "balance": 955838394.0,
      "source_page": 35,
      "row_order": 7
    },
    {
      "date": "1405/02/06",
      "time": "20:09:02",
      "description": "343313664119 ش پ 664119 خرید کالا و خدمات از پایانه فروش 08158181 به پرداخت ملت ش م",
      "deposit": 0.0,
      "withdrawal": 60000000.0,
      "balance": 958838394.0,
      "source_page": 35,
      "row_order": 8
    },
    {
      "date": "1405/02/06",
      "time": "19:49:53",
      "description": "1405020605638219495352310 برداشت از سپرده بابت کارمزد انتقال پل: - کد پیگیری تراکنش اصلی:",
      "deposit": 0.0,
      "withdrawal": 10000.0,
      "balance": 1018838394.0,
      "source_page": 35,
      "row_order": 9
    },
    {
      "date": "1405/02/06",
      "time": "19:49:53",
      "description": "اقاخانی - کد پیگیری تراکنش: 1405020605638219495352310 انتقال پل به شماره شبا: IR820120010000004289595123 بانک ملت بنام فرزاد",
      "deposit": 0.0,
      "withdrawal": 50000000.0,
      "balance": 1018848394.0,
      "source_page": 35,
      "row_order": 10
    },
    {
      "date": "1405/02/06",
      "time": "19:48:25",
      "description": "امیرحسین حقی ایدلو - شماره پیگیری تراکنش: 140502060192784251 انتقال پایا از شماره شبا: IR890190000000204209008009 بانک صادرات بنام:",
      "deposit": 137000000.0,
      "withdrawal": 0.0,
      "balance": 1068848394.0,
      "source_page": 35,
      "row_order": 11
    },
    {
      "date": "1405/02/06",
      "time": "19:06:37",
      "description": "1405020605637219063710810 برداشت از سپرده بابت کارمزد انتقال پل: - کد پیگیری تراکنش اصلی:",
      "deposit": 0.0,
      "withdrawal": 20000.0,
      "balance": 931848394.0,
      "source_page": 35,
      "row_order": 12
    },
    {
      "date": "1405/02/06",
      "time": "19:06:37",
      "description": "پیرانی - کد پیگیری تراکنش: 1405020605637219063710810 انتقال پل به شماره شبا: IR490170000000102506208009 بانک ملی بنام حسن",
      "deposit": 0.0,
      "withdrawal": 100000000.0,
      "balance": 931868394.0,
      "source_page": 35,
      "row_order": 13
    },
    {
      "date": "1405/02/06",
      "time": "17:20:23",
      "description": "م 750063115543 ش پ 745544 خرید کالا و خدمات از پایانه فروش 44983726 تجارت الکترونیک پارسیان ش",
      "deposit": 0.0,
      "withdrawal": 79000000.0,
      "balance": 1031868394.0,
      "source_page": 35,
      "row_order": 14
    }
  ],
  "extraction_status": "ok",
  "notes": "camelot: 14 تراکنش استخراج شد"
}