{
  "page_number": 97,
  "account_holder_name": null,
  "transactions": [
    {
      "date": "1405/03/14",
      "time": "02:59",
      "description": "انتقال MOB",
      "deposit": 0.0,
      "withdrawal": 450.0,
      "balance": 97327217.0,
      "source_page": 97,
      "row_order": 0
    },
    {
      "date": "1405/03/14",
      "time": "16:05",
      "description": "انتقال MOB انتقال از حساب 1021354211 شرح: 03-",
      "deposit": 817000000.0,
      "withdrawal": 0.0,
      "balance": 914327217.0,
      "source_page": 97,
      "row_order": 1
    },
    {
      "date": "1405/03/14",
      "time": "16:24",
      "description": "انتقال MOB انتقال به حساب 1101249547 شرح: 01-",
      "deposit": 0.0,
      "withdrawal": 633300000.0,
      "balance": 281027217.0,
      "source_page": 97,
      "row_order": 2
    },
    {
      "date": "1405/03/14",
      "time": "16:24",
      "description": "انتقال MOB",
      "deposit": 0.0,
      "withdrawal": 450.0,
      "balance": 281026767.0,
      "source_page": 97,
      "row_order": 3
    },
    {
      "date": "1405/03/14",
      "time": "16:29",
      "description": "انتقال MOB انتقال به حساب 1111153910 شرح: 01-",
      "deposit": 0.0,
      "withdrawal": 135000000.0,
      "balance": 146026767.0,
      "source_page": 97,
      "row_order": 4
    },
    {
      "date": "1405/03/14",
      "time": "16:29",
      "description": "انتقال MOB",
      "deposit": 0.0,
      "withdrawal": 450.0,
      "balance": 146026317.0,
      "source_page": 97,
      "row_order": 5
    },
    {
      "date": "1405/03/14",
      "time": "16:32",
      "description": "انتقال MOB انتقال به حساب 252709100 شرح: 01-",
      "deposit": 0.0,
      "withdrawal": 50000000.0,
      "balance": 96026317.0,
      "source_page": 97,
      "row_order": 6
    },
    {
      "date": "1405/03/14",
      "time": "16:32",
      "description": "انتقال MOB",
      "deposit": 0.0,
      "withdrawal": 450.0,
      "balance": 96025867.0,
      "source_page": 97,
      "row_order": 7
    },
    {
      "date": "1405/03/14",
      "time": "18:53",
      "description": "انتقال MOB انتقال به حساب 827393445 شرح: 01-",
      "deposit": 0.0,
      "withdrawal": 5700000.0,
      "balance": 90325867.0,
      "source_page": 97,
      "row_order": 8
    },
    {
      "date": "1405/03/14",
      "time": "18:53",
      "description": "انتقال MOB",
      "deposit": 0.0,
      "withdrawal": 450.0,
      "balance": 90325417.0,
      "source_page": 97,
      "row_order": 9
    },
    {
      "date": "1405/03/14",
      "time": "20:57",
      "description": "انتقال MOB انتقال به حساب 922985536 شرح: 01-",
      "deposit": 0.0,
      "withdrawal": 90000000.0,
      "balance": 325417.0,
      "source_page": 97,
      "row_order": 10
    },
    {
      "date": "1405/03/14",
      "time": "20:57",
      "description": "انتقال MOB",
      "deposit": 0.0,
      "withdrawal": 450.0,
      "balance": 324967.0,
      "source_page": 97,
      "row_order": 11
    },
    {
      "date": "1405/03/15",
      "time": "11:30",
      "description": "انتقال MOB انتقال از حساب 1031473123 شرح: 18-",
      "deposit": 1106000000.0,
      "withdrawal": 0.0,
      "balance": 1106324967.0,
      "source_page": 97,
      "row_order": 12
    },
    {
      "date": "1405/03/15",
      "time": "12:20",
      "description": "انتقال MOB انتقال به حساب 1112647669 شرح: 01-",
      "deposit": 0.0,
      "withdrawal": 1000000000.0,
      "balance": 106324967.0,
      "source_page": 97,
      "row_order": 13
    },
    {
      "date": "1405/03/15",
      "time": "12:20",
      "description": "انتقال MOB",
      "deposit": 0.0,
      "withdrawal": 450.0,
      "balance": 106324517.0,
      "source_page": 97,
      "row_order": 14
    },
    {
      "date": "1405/03/15",
      "time": "12:22",
      "description": "انتقال MOB انتقال به حساب 1112647669 شرح: 01-",
      "deposit": 0.0,
      "withdrawal": 86600000.0,
      "balance": 19724517.0,
      "source_page": 97,
      "row_order": 15
    },
    {
      "date": "1405/03/15",
      "time": "12:22",
      "description": "انتقال MOB",
      "deposit": 0.0,
      "withdrawal": 450.0,
      "balance": 19724067.0,
      "source_page": 97,
      "row_order": 16
    },
    {
      "date": "1405/03/15",
      "time": "12:23",
      "description": "انتقال MOB انتقال به حساب 1118156368 شرح: 10-",
      "deposit": 0.0,
      "withdrawal": 18000000.0,
      "balance": 1724067.0,
      "source_page": 97,
      "row_order": 17
    },
    {
      "date": "1405/03/15",
      "time": "12:23",
      "description": "انتقال MOB",
      "deposit": 0.0,
      "withdrawal": 450.0,
      "balance": 1723617.0,
      "source_page": 97,
      "row_order": 18
    },
    {
      "date": "1405/03/15",
      "time": "13:09",
      "description": "انتقال MOB انتقال از حساب 295323717 شرح: 18-",
      "deposit": 980000000.0,
      "withdrawal": 0.0,
      "balance": 981723617.0,
      "source_page": 98,
      "row_order": 19
    },
    {
      "date": "1405/03/15",
      "time": "16:34",
      "description": "انتقال MOB انتقال به حساب 1143391470 شرح: 01-",
      "deposit": 0.0,
      "withdrawal": 333300000.0,
      "balance": 648423617.0,
      "source_page": 98,
      "row_order": 20
    },
    {
      "date": "1405/03/15",
      "time": "16:34",
      "description": "انتقال MOB",
      "deposit": 0.0,
      "withdrawal": 450.0,
      "balance": 648423167.0,
      "source_page": 98,
      "row_order": 21
    },
    {
      "date": "1405/03/15",
      "time": "16:34",
      "description": "انتقال MOB انتقال به حساب 680740697",
      "deposit": 0.0,
      "withdrawal": 400000000.0,
      "balance": 248423167.0,
      "source_page": 98,
      "row_order": 22
    },
    {
      "date": "1405/03/15",
      "time": "16:34",
      "description": "انتقال MOB",
      "deposit": 0.0,
      "withdrawal": 450.0,
      "balance": 248422717.0,
      "source_page": 98,
      "row_order": 23
    },
    {
      "date": "1405/03/15",
      "time": "17:09",
      "description": "انتقال MOB انتقال از حساب 997356600 شرح: 18-",
      "deposit": 506000000.0,
      "withdrawal": 0.0,
      "balance": 754422717.0,
      "source_page": 98,
      "row_order": 24
    },
    {
      "date": "1405/03/15",
      "time": "18:00",
      "description": "انتقال MOB انتقال از حساب 997356600 شرح: 18-",
      "deposit": 505000000.0,
      "withdrawal": 0.0,
      "balance": 1259422717.0,
      "source_page": 98,
      "row_order": 25
    },
    {
      "date": "1405/03/15",
      "time": "18:04",
      "description": "واریز پل نام واریز کننده: فاطمه تازه وارد کد پیگیری: 140503150123180433839 سامانه انتقال وجه: پل درگاه انتقال دهنده: شعبه شماره شبا مبداء: IR090120010000009987728353 بانک مبداء: ملت",
      "deposit": 440000000.0,
      "withdrawal": 0.0,
      "balance": 1699422717.0,
      "source_page": 98,
      "row_order": 26
    },
    {
      "date": "1405/03/15",
      "time": "19:32",
      "description": "انتقال MOB انتقال به حساب 1055444559 شرح: 01-",
      "deposit": 0.0,
      "withdrawal": 190000000.0,
      "balance": 1509422717.0,
      "source_page": 98,
      "row_order": 27
    },
    {
      "date": "1405/03/15",
      "time": "19:32",
      "description": "انتقال MOB",
      "deposit": 0.0,
      "withdrawal": 450.0,
      "balance": 1509422267.0,
      "source_page": 98,
      "row_order": 28
    },
    {
      "date": "1405/03/15",
      "time": "19:37",
      "description": "انتقال MOB انتقال به حساب 1112647669 شرح: 01-",
      "deposit": 0.0,
      "withdrawal": 1000000000.0,
      "balance": 509422267.0,
      "source_page": 98,
      "row_order": 29
    },
    {
      "date": "1405/03/15",
      "time": "19:37",
      "description": "انتقال MOB",
      "deposit": 0.0,
      "withdrawal": 450.0,
      "balance": 509421817.0,
      "source_page": 98,
      "row_order": 30
    },
    {
      "date": "1405/03/15",
      "time": "20:36",
      "description": "انتقال MOB انتقال به حساب 252712919",
      "deposit": 0.0,
      "withdrawal": 75000000.0,
      "balance": 434421817.0,
      "source_page": 98,
      "row_order": 31
    },
    {
      "date": "1405/03/15",
      "time": "20:36",
      "description": "انتقال MOB",
      "deposit": 0.0,
      "withdrawal": 450.0,
      "balance": 434421367.0,
      "source_page": 98,
      "row_order": 32
    },
    {
      "date": "1405/03/15",
      "time": "21:11",
      "description": "انتقال MOB انتقال به حساب 760004645",
      "deposit": 0.0,
      "withdrawal": 1800000.0,
      "balance": 432621367.0,
      "source_page": 98,
      "row_order": 33
    },
    {
      "date": "1405/03/15",
      "time": "21:11",
      "description": "انتقال MOB",
      "deposit": 0.0,
      "withdrawal": 450.0,
      "balance": 432620917.0,
      "source_page": 98,
      "row_order": 34
    },
    {
      "date": "1405/03/15",
      "time": "21:14",
      "description": "انتقال MOB انتقال به حساب 650274890 شرح: 01-",
      "deposit": 0.0,
      "withdrawal": 50000000.0,
      "balance": 382620917.0,
      "source_page": 99,
      "row_order": 35
    },
    {
      "date": "1405/03/15",
      "time": "21:14",
      "description": "انتقال MOB",
      "deposit": 0.0,
      "withdrawal": 450.0,
      "balance": 382620467.0,
      "source_page": 99,
      "row_order": 36
    },
    {
      "date": "1405/03/16",
      "time": "02:49",
      "description": "انتقال MOB انتقال از حساب 956424922 شرح: 18-",
      "deposit": 823500000.0,
      "withdrawal": 0.0,
      "balance": 1206120467.0,
      "source_page": 99,
      "row_order": 37
    },
    {
      "date": "1405/03/16",
      "time": "02:50",
      "description": "انتقال MOB انتقال به حساب 1112647669 شرح: 01-",
      "deposit": 0.0,
      "withdrawal": 476600000.0,
      "balance": 729520467.0,
      "source_page": 99,
      "row_order": 38
    },
    {
      "date": "1405/03/16",
      "time": "02:50",
      "description": "انتقال MOB",
      "deposit": 0.0,
      "withdrawal": 450.0,
      "balance": 729520017.0,
      "source_page": 99,
      "row_order": 39
    },
    {
      "date": "1405/03/16",
      "time": "02:50",
      "description": "انتقال MOB انتقال به حساب 1112647669 شرح: 01-",
      "deposit": 0.0,
      "withdrawal": 480000000.0,
      "balance": 249520017.0,
      "source_page": 99,
      "row_order": 40
    },
    {
      "date": "1405/03/16",
      "time": "02:50",
      "description": "انتقال MOB",
      "deposit": 0.0,
      "withdrawal": 450.0,
      "balance": 249519567.0,
      "source_page": 99,
      "row_order": 41
    },
    {
      "date": "1405/03/16",
      "time": "02:50",
      "description": "انتقال MOB انتقال از حساب 1118156368 شرح: 10-",
      "deposit": 50000000.0,
      "withdrawal": 0.0,
      "balance": 299519567.0,
      "source_page": 99,
      "row_order": 42
    },
    {
      "date": "1405/03/16",
      "time": "02:50",
      "description": "انتقال MOB انتقال به حساب 1012948535 شرح: 01-",
      "deposit": 0.0,
      "withdrawal": 250000000.0,
      "balance": 49519567.0,
      "source_page": 99,
      "row_order": 43
    },
    {
      "date": "1405/03/16",
      "time": "02:50",
      "description": "انتقال MOB",
      "deposit": 0.0,
      "withdrawal": 450.0,
      "balance": 49519117.0,
      "source_page": 99,
      "row_order": 44
    },
    {
      "date": "1405/03/16",
      "time": "11:45",
      "description": "انتقال MOB انتقال از حساب 273605845 شرح: 18-",
      "deposit": 1128000000.0,
      "withdrawal": 0.0,
      "balance": 1177519117.0,
      "source_page": 99,
      "row_order": 45
    },
    {
      "date": "1405/03/16",
      "time": "12:31",
      "description": "انتقال MOB انتقال به حساب 928116842 شرح: 01-",
      "deposit": 0.0,
      "withdrawal": 600000.0,
      "balance": 1176919117.0,
      "source_page": 99,
      "row_order": 46
    },
    {
      "date": "1405/03/16",
      "time": "12:31",
      "description": "انتقال MOB",
      "deposit": 0.0,
      "withdrawal": 450.0,
      "balance": 1176918667.0,
      "source_page": 99,
      "row_order": 47
    },
    {
      "date": "1405/03/16",
      "time": "14:33",
      "description": "برداشت پل نام دریافت کننده: مهدي عزت پور کد پیگیری: 14050316016307030733141424 سامانه انتقال وجه: پل درگاه انتقال دهنده: همراه بانک شماره شبا مقصد: IR230170000000231688127009 بانک مقصد: ملي",
      "deposit": 0.0,
      "withdrawal": 100000000.0,
      "balance": 1076918667.0,
      "source_page": 99,
      "row_order": 48
    },
    {
      "date": "1405/03/16",
      "time": "14:33",
      "description": "کارمزد پل",
      "deposit": 0.0,
      "withdrawal": 20000.0,
      "balance": 1076898667.0,
      "source_page": 99,
      "row_order": 49
    },
    {
      "date": "1405/03/16",
      "time": "16:05",
      "description": "انتقال MOB انتقال به حساب 1151250268 شرح: 01-",
      "deposit": 0.0,
      "withdrawal": 500000000.0,
      "balance": 576898667.0,
      "source_page": 99,
      "row_order": 50
    },
    {
      "date": "1405/03/16",
      "time": "16:05",
      "description": "انتقال MOB",
      "deposit": 0.0,
      "withdrawal": 450.0,
      "balance": 576898217.0,
      "source_page": 99,
      "row_order": 51
    },
    {
      "date": "1405/03/16",
      "time": "17:09",
      "description": "انتقال IB انتقال از حساب 956424922 شرح: 18",
      "deposit": 518000000.0,
      "withdrawal": 0.0,
      "balance": 1094898217.0,
      "source_page": 100,
      "row_order": 52
    },
    {
      "date": "1405/03/16",
      "time": "17:09",
      "description": "انتقال MOB انتقال به حساب 912595026 شرح: 01-",
      "deposit": 0.0,
      "withdrawal": 2000000.0,
      "balance": 1092898217.0,
      "source_page": 100,
      "row_order": 53
    },
    {
      "date": "1405/03/16",
      "time": "17:09",
      "description": "انتقال MOB",
      "deposit": 0.0,
      "withdrawal": 450.0,
      "balance": 1092897767.0,
      "source_page": 100,
      "row_order": 54
    },
    {
      "date": "1405/03/16",
      "time": "17:22",
      "description": "انتقال MOB انتقال به حساب 1112647669 شرح: 01-",
      "deposit": 0.0,
      "withdrawal": 1000000000.0,
      "balance": 92897767.0,
      "source_page": 100,
      "row_order": 55
    },
    {
      "date": "1405/03/16",
      "time": "17:22",
      "description": "انتقال MOB",
      "deposit": 0.0,
      "withdrawal": 450.0,
      "balance": 92897317.0,
      "source_page": 100,
      "row_order": 56
    },
    {
      "date": "1405/03/16",
      "time": "17:25",
      "description": "انتقال MOB انتقال به حساب 1084415976 شرح: 01-",
      "deposit": 0.0,
      "withdrawal": 20000000.0,
      "balance": 72897317.0,
      "source_page": 100,
      "row_order": 57
    },
    {
      "date": "1405/03/16",
      "time": "17:25",
      "description": "انتقال MOB",
      "deposit": 0.0,
      "withdrawal": 450.0,
      "balance": 72896867.0,
      "source_page": 100,
      "row_order": 58
    },
    {
      "date": "1405/03/16",
      "time": "18:36",
      "description": "انتقال MOB انتقال به حساب 865409600 شرح: 01-",
      "deposit": 0.0,
      "withdrawal": 2000000.0,
      "balance": 70896867.0,
      "source_page": 100,
      "row_order": 59
    },
    {
      "date": "1405/03/16",
      "time": "18:36",
      "description": "انتقال MOB",
      "deposit": 0.0,
      "withdrawal": 450.0,
      "balance": 70896417.0,
      "source_page": 100,
      "row_order": 60
    },
    {
      "date": "1405/03/16",
      "time": "19:22",
      "description": "انتقال MOB انتقال به حساب 1088720713 شرح: 01-",
      "deposit": 0.0,
      "withdrawal": 38000000.0,
      "balance": 32896417.0,
      "source_page": 100,
      "row_order": 61
    },
    {
      "date": "1405/03/16",
      "time": "19:22",
      "description": "انتقال MOB",
      "deposit": 0.0,
      "withdrawal": 450.0,
      "balance": 32895967.0,
      "source_page": 100,
      "row_order": 62
    },
    {
      "date": "1405/03/16",
      "time": "19:48",
      "description": "برداشت پل نام دریافت کننده: مهدي لجوردي کد پیگیری: 14050316016301031248193934 سامانه انتقال وجه: پل درگاه انتقال دهنده: همراه بانک شماره شبا مقصد: IR160170000000369096676001 بانک مقصد: ملي",
      "deposit": 0.0,
      "withdrawal": 20000000.0,
      "balance": 12895967.0,
      "source_page": 100,
      "row_order": 63
    },
    {
      "date": "1405/03/16",
      "time": "19:48",
      "description": "کارمزد پل",
      "deposit": 0.0,
      "withdrawal": 5000.0,
      "balance": 12890967.0,
      "source_page": 100,
      "row_order": 64
    },
    {
      "date": "1405/03/17",
      "time": "03:56",
      "description": "برداشت پل نام دریافت کننده: سجاد شنبدي کد پیگیری: 14050317016303031256039553 سامانه انتقال وجه: پل درگاه انتقال دهنده: همراه بانک شماره شبا مقصد: IR190170000000370903283002 بانک مقصد: ملي",
      "deposit": 0.0,
      "withdrawal": 2000000.0,
      "balance": 10890967.0,
      "source_page": 100,
      "row_order": 65
    },
    {
      "date": "1405/03/17",
      "time": "03:56",
      "description": "کارمزد پل",
      "deposit": 0.0,
      "withdrawal": 5000.0,
      "balance": 10885967.0,
      "source_page": 100,
      "row_order": 66
    }
  ],
  "extraction_status": "ok",
  "notes": "استخراج تصویری از صفحات 97-100 (4 تصویر)"
}